[
	{
		"op": "add",
		"path": "/class",
		"value": "ImmersiveBag",
		"file": "game:itemtypes/wearable/bag/backpack.json"
	},
	{
		"op": "add",
		"path": "/behaviors/0",
		"value": { "name": "ImmersiveBackpackPlacement" },
		"file": "game:itemtypes/wearable/bag/backpack.json"
	},
	{
		"op": "add",
		"path": "/attributes/immersiveBackpackByType",
		"value": {
			"*-normal": {
				"attachmentPoints": [
					{ "code": "left_pouch",        "categories": ["pouch"] },
					{ "code": "right_pouch",       "categories": ["pouch"] },
					{ "code": "front_left_pouch",  "categories": ["pouch"] },
					{ "code": "front_right_pouch", "categories": ["pouch"] },
					{ "code": "lantern",           "categories": ["light"] },
					{ "code": "left_strap",        "categories": ["toolstrap"] },
					{ "code": "right_strap",       "categories": ["toolstrap"] }
				]
			},
			"*-sturdy": {
				"attachmentPoints": [
					{ "code": "lantern",           "categories": ["light"] },
					{ "code": "lower_left_pouch",  "categories": ["pouch"] },
					{ "code": "lower_right_pouch", "categories": ["pouch"] },
					{ "code": "lower_front_left",  "categories": ["pouch", "sack"] },
					{ "code": "lower_front_right", "categories": ["pouch", "sack"] },
					{ "code": "upper_left_pouch",  "categories": ["pouch"] },
					{ "code": "upper_right_pouch", "categories": ["pouch"] }
				]
			}
		},
		"file": "game:itemtypes/wearable/bag/backpack.json"
	}
]
